my_unit_converter/Conversion.py
my_unit_converter/__init__.py
my_unit_converter/unit_converter_test.py
my_unit_converter-0.1.7.dist-info/LICENSE
my_unit_converter-0.1.7.dist-info/METADATA
my_unit_converter-0.1.7.dist-info/WHEEL
my_unit_converter-0.1.7.dist-info/top_level.txt
my_unit_converter-0.1.7.dist-info/RECORD
