Metadata-Version: 2.1
Name: my-unit-converter
Version: 0.1.7
Summary: A library for converting various units of measurement.
Home-page: https://github.com/joshiess13468/unit_converter
Author: Amwine Josh
Author-email: joshamwine@gmail.com
Classifier: Programming Language :: Python :: 3
Classifier: License :: OSI Approved :: MIT License
Classifier: Operating System :: OS Independent
License-File: LICENSE
